{
  "info": {
    "_postman_id": "d5b6c93d-8e80-4a62-9364-ecatalogue-group-menu",
    "name": "E-Catalogue Backend API",
    "description": "Workflow API authentication, Group Menu, Menu, Permission, Role, dan User termasuk pengaturan role dan branch. Isi collection variable username dan password, lalu jalankan request berurutan.",
    "schema": "https://schema.getpostman.com/json/collection/v2.1.0/collection.json"
  },
  "auth": {
    "type": "bearer",
    "bearer": [
      {
        "key": "token",
        "value": "{{accessToken}}",
        "type": "string"
      }
    ]
  },
  "event": [
    {
      "listen": "test",
      "script": {
        "type": "text/javascript",
        "exec": [
          "pm.test('Response JSON', () => pm.expect(pm.response.headers.get('Content-Type')).to.include('application/json'));",
          "const response = pm.response.json();",
          "pm.test('Format response standar', () => {",
          "  pm.expect(response).to.have.property('success');",
          "  pm.expect(response).to.have.property('message');",
          "});"
        ]
      }
    }
  ],
  "variable": [
    {
      "key": "baseUrl",
      "value": "http://localhost:3000"
    },
    {
      "key": "username",
      "value": "admin"
    },
    {
      "key": "password",
      "value": ""
    },
    {
      "key": "accessToken",
      "value": ""
    },
    {
      "key": "refreshToken",
      "value": ""
    },
    {
      "key": "testSuffix",
      "value": ""
    },
    {
      "key": "groupMenuId",
      "value": ""
    },
    {
      "key": "menuId",
      "value": ""
    },
    {
      "key": "permissionId",
      "value": ""
    },
    {
      "key": "roleId",
      "value": ""
    },
    {
      "key": "salesRoleId",
      "value": ""
    },
    {
      "key": "userId",
      "value": ""
    },
    {
      "key": "branchId",
      "value": ""
    },
    {
      "key": "merekId",
      "value": ""
    },
    {
      "key": "tipeId",
      "value": ""
    },
    {
      "key": "vendorId",
      "value": ""
    },
    {
      "key": "branchImageId",
      "value": ""
    },
    {
      "key": "LeasingId",
      "value": ""
    },
    {
      "key": "SumberLeadId",
      "value": ""
    },
    {
      "key": "PengecekanId",
      "value": ""
    },
    {
      "key": "KategoriPengeluaranId",
      "value": ""
    },
    {
      "key": "MetodePembayaranId",
      "value": ""
    },
    {
      "key": "DokumenId",
      "value": ""
    },
    {
      "key": "PerlengkapanId",
      "value": ""
    }
  ],
  "item": [
    {
      "name": "00 Health",
      "item": [
        {
          "name": "Health Check",
          "request": {
            "auth": {
              "type": "noauth"
            },
            "method": "GET",
            "url": "{{baseUrl}}/health"
          },
          "event": [
            {
              "listen": "test",
              "script": {
                "type": "text/javascript",
                "exec": [
                  "pm.test('Status 200', () => pm.response.to.have.status(200));"
                ]
              }
            }
          ]
        }
      ]
    },
    {
      "name": "01 Authentication",
      "item": [
        {
          "name": "Login",
          "request": {
            "auth": {
              "type": "noauth"
            },
            "method": "POST",
            "header": [
              {
                "key": "Content-Type",
                "value": "application/json"
              }
            ],
            "body": {
              "mode": "raw",
              "raw": "{\n  \"identifier\": \"{{username}}\",\n  \"password\": \"{{password}}\"\n}"
            },
            "url": "{{baseUrl}}/api/v1/auth/login"
          },
          "event": [
            {
              "listen": "prerequest",
              "script": {
                "type": "text/javascript",
                "exec": [
                  "pm.collectionVariables.set('testSuffix', Date.now().toString());"
                ]
              }
            },
            {
              "listen": "test",
              "script": {
                "type": "text/javascript",
                "exec": [
                  "pm.test('Status 200', () => pm.response.to.have.status(200));",
                  "const data = pm.response.json().data;",
                  "pm.collectionVariables.set('accessToken', data.accessToken);",
                  "pm.collectionVariables.set('refreshToken', data.refreshToken);"
                ]
              }
            }
          ]
        },
        {
          "name": "Get Current User",
          "request": {
            "method": "GET",
            "url": "{{baseUrl}}/api/v1/auth/me"
          },
          "event": [
            {
              "listen": "test",
              "script": {
                "type": "text/javascript",
                "exec": [
                  "pm.test('Status 200', () => pm.response.to.have.status(200));",
                  "pm.test('groupMenus tersedia', () => pm.expect(pm.response.json().data.groupMenus).to.be.an('array'));"
                ]
              }
            }
          ]
        },
        {
          "name": "Refresh Token",
          "request": {
            "auth": {
              "type": "noauth"
            },
            "method": "POST",
            "header": [
              {
                "key": "Content-Type",
                "value": "application/json"
              }
            ],
            "body": {
              "mode": "raw",
              "raw": "{\n  \"refreshToken\": \"{{refreshToken}}\"\n}"
            },
            "url": "{{baseUrl}}/api/v1/auth/refresh"
          },
          "event": [
            {
              "listen": "test",
              "script": {
                "type": "text/javascript",
                "exec": [
                  "pm.test('Status 200', () => pm.response.to.have.status(200));",
                  "const data = pm.response.json().data;",
                  "pm.collectionVariables.set('accessToken', data.accessToken);",
                  "pm.collectionVariables.set('refreshToken', data.refreshToken);"
                ]
              }
            }
          ]
        }
      ]
    },
    {
      "name": "02 Group Menu, Menu & Permission",
      "item": [
        {
          "name": "List Group Menus",
          "request": {
            "method": "GET",
            "url": "{{baseUrl}}/api/v1/menus/groups?page=1&limit=20&search="
          },
          "event": [
            {
              "listen": "test",
              "script": {
                "type": "text/javascript",
                "exec": [
                  "pm.test('Status 200', () => pm.response.to.have.status(200));"
                ]
              }
            }
          ]
        },
        {
          "name": "Create Group Menu",
          "request": {
            "method": "POST",
            "header": [
              {
                "key": "Content-Type",
                "value": "application/json"
              }
            ],
            "body": {
              "mode": "raw",
              "raw": "{\n  \"name\": \"Postman Group {{testSuffix}}\",\n  \"code\": \"POSTMAN_GROUP_{{testSuffix}}\",\n  \"description\": \"Group pengujian Postman\",\n  \"icon\": \"folder\",\n  \"sortOrder\": 900,\n  \"isActive\": true\n}"
            },
            "url": "{{baseUrl}}/api/v1/menus/groups"
          },
          "event": [
            {
              "listen": "test",
              "script": {
                "type": "text/javascript",
                "exec": [
                  "pm.test('Status 201', () => pm.response.to.have.status(201));",
                  "pm.collectionVariables.set('groupMenuId', pm.response.json().data.id);"
                ]
              }
            }
          ]
        },
        {
          "name": "Get Group Menu Detail",
          "request": {
            "method": "GET",
            "url": "{{baseUrl}}/api/v1/menus/groups/{{groupMenuId}}"
          },
          "event": [
            {
              "listen": "test",
              "script": {
                "type": "text/javascript",
                "exec": [
                  "pm.test('Status 200', () => pm.response.to.have.status(200));"
                ]
              }
            }
          ]
        },
        {
          "name": "Update Group Menu",
          "request": {
            "method": "PATCH",
            "header": [
              {
                "key": "Content-Type",
                "value": "application/json"
              }
            ],
            "body": {
              "mode": "raw",
              "raw": "{\n  \"name\": \"Postman Group Updated {{testSuffix}}\",\n  \"sortOrder\": 901\n}"
            },
            "url": "{{baseUrl}}/api/v1/menus/groups/{{groupMenuId}}"
          },
          "event": [
            {
              "listen": "test",
              "script": {
                "type": "text/javascript",
                "exec": [
                  "pm.test('Status 200', () => pm.response.to.have.status(200));"
                ]
              }
            }
          ]
        },
        {
          "name": "Create Menu",
          "request": {
            "method": "POST",
            "header": [
              {
                "key": "Content-Type",
                "value": "application/json"
              }
            ],
            "body": {
              "mode": "raw",
              "raw": "{\n  \"name\": \"Postman Menu {{testSuffix}}\",\n  \"code\": \"POSTMAN_MENU_{{testSuffix}}\",\n  \"description\": \"Menu pengujian Postman\",\n  \"path\": \"/postman/menu\",\n  \"icon\": \"test\",\n  \"sortOrder\": 10,\n  \"isActive\": true\n}"
            },
            "url": "{{baseUrl}}/api/v1/menus/groups/{{groupMenuId}}/items"
          },
          "event": [
            {
              "listen": "test",
              "script": {
                "type": "text/javascript",
                "exec": [
                  "pm.test('Status 201', () => pm.response.to.have.status(201));",
                  "pm.collectionVariables.set('menuId', pm.response.json().data.id);"
                ]
              }
            }
          ]
        },
        {
          "name": "Get Menu Detail",
          "request": {
            "method": "GET",
            "url": "{{baseUrl}}/api/v1/menus/{{menuId}}"
          },
          "event": [
            {
              "listen": "test",
              "script": {
                "type": "text/javascript",
                "exec": [
                  "pm.test('Status 200', () => pm.response.to.have.status(200));"
                ]
              }
            }
          ]
        },
        {
          "name": "Update Menu",
          "request": {
            "method": "PATCH",
            "header": [
              {
                "key": "Content-Type",
                "value": "application/json"
              }
            ],
            "body": {
              "mode": "raw",
              "raw": "{\n  \"name\": \"Postman Menu Updated {{testSuffix}}\",\n  \"sortOrder\": 11\n}"
            },
            "url": "{{baseUrl}}/api/v1/menus/{{menuId}}"
          },
          "event": [
            {
              "listen": "test",
              "script": {
                "type": "text/javascript",
                "exec": [
                  "pm.test('Status 200', () => pm.response.to.have.status(200));"
                ]
              }
            }
          ]
        },
        {
          "name": "Create Permission",
          "request": {
            "method": "POST",
            "header": [
              {
                "key": "Content-Type",
                "value": "application/json"
              }
            ],
            "body": {
              "mode": "raw",
              "raw": "{\n  \"name\": \"Postman Read\",\n  \"code\": \"POSTMAN_READ_{{testSuffix}}\",\n  \"description\": \"Permission pengujian Postman\"\n}"
            },
            "url": "{{baseUrl}}/api/v1/menus/{{menuId}}/permissions"
          },
          "event": [
            {
              "listen": "test",
              "script": {
                "type": "text/javascript",
                "exec": [
                  "pm.test('Status 201', () => pm.response.to.have.status(201));",
                  "pm.collectionVariables.set('permissionId', pm.response.json().data.id);"
                ]
              }
            }
          ]
        },
        {
          "name": "Update Permission",
          "request": {
            "method": "PATCH",
            "header": [
              {
                "key": "Content-Type",
                "value": "application/json"
              }
            ],
            "body": {
              "mode": "raw",
              "raw": "{\n  \"name\": \"Postman Read Updated\"\n}"
            },
            "url": "{{baseUrl}}/api/v1/menus/{{menuId}}/permissions/{{permissionId}}"
          },
          "event": [
            {
              "listen": "test",
              "script": {
                "type": "text/javascript",
                "exec": [
                  "pm.test('Status 200', () => pm.response.to.have.status(200));"
                ]
              }
            }
          ]
        }
      ]
    },
    {
      "name": "03 Role",
      "item": [
        {
          "name": "List Roles",
          "request": {
            "method": "GET",
            "url": "{{baseUrl}}/api/v1/roles?page=1&limit=100&search="
          },
          "event": [
            {
              "listen": "test",
              "script": {
                "type": "text/javascript",
                "exec": [
                  "pm.test('Status 200', () => pm.response.to.have.status(200));",
                  "const sales = pm.response.json().data.find((role) => role.code === 'SALES');",
                  "pm.test('Role SALES tersedia', () => pm.expect(sales).to.exist);",
                  "if (sales) pm.collectionVariables.set('salesRoleId', sales.id);"
                ]
              }
            }
          ]
        },
        {
          "name": "Create Role",
          "request": {
            "method": "POST",
            "header": [
              {
                "key": "Content-Type",
                "value": "application/json"
              }
            ],
            "body": {
              "mode": "raw",
              "raw": "{\n  \"name\": \"Postman Role {{testSuffix}}\",\n  \"code\": \"POSTMAN_ROLE_{{testSuffix}}\",\n  \"description\": \"Role pengujian Postman\",\n  \"isActive\": true\n}"
            },
            "url": "{{baseUrl}}/api/v1/roles"
          },
          "event": [
            {
              "listen": "test",
              "script": {
                "type": "text/javascript",
                "exec": [
                  "pm.test('Status 201', () => pm.response.to.have.status(201));",
                  "pm.collectionVariables.set('roleId', pm.response.json().data.id);"
                ]
              }
            }
          ]
        },
        {
          "name": "Get Role Detail",
          "request": {
            "method": "GET",
            "url": "{{baseUrl}}/api/v1/roles/{{roleId}}"
          },
          "event": [
            {
              "listen": "test",
              "script": {
                "type": "text/javascript",
                "exec": [
                  "pm.test('Status 200', () => pm.response.to.have.status(200));"
                ]
              }
            }
          ]
        },
        {
          "name": "Update Role",
          "request": {
            "method": "PATCH",
            "header": [
              {
                "key": "Content-Type",
                "value": "application/json"
              }
            ],
            "body": {
              "mode": "raw",
              "raw": "{\n  \"name\": \"Postman Role Updated {{testSuffix}}\"\n}"
            },
            "url": "{{baseUrl}}/api/v1/roles/{{roleId}}"
          },
          "event": [
            {
              "listen": "test",
              "script": {
                "type": "text/javascript",
                "exec": [
                  "pm.test('Status 200', () => pm.response.to.have.status(200));"
                ]
              }
            }
          ]
        },
        {
          "name": "Set Role Permissions",
          "request": {
            "method": "PUT",
            "header": [
              {
                "key": "Content-Type",
                "value": "application/json"
              }
            ],
            "body": {
              "mode": "raw",
              "raw": "{\n  \"permissionIds\": [\n    \"{{permissionId}}\"\n  ]\n}"
            },
            "url": "{{baseUrl}}/api/v1/roles/{{roleId}}/permissions"
          },
          "event": [
            {
              "listen": "test",
              "script": {
                "type": "text/javascript",
                "exec": [
                  "pm.test('Status 200', () => pm.response.to.have.status(200));"
                ]
              }
            }
          ]
        }
      ]
    },
    {
      "name": "04 User",
      "item": [
        {
          "name": "List Users",
          "request": {
            "method": "GET",
            "url": "{{baseUrl}}/api/v1/users?page=1&limit=20&search=&roleId=&isActive=true"
          },
          "event": [
            {
              "listen": "test",
              "script": {
                "type": "text/javascript",
                "exec": [
                  "pm.test('Status 200', () => pm.response.to.have.status(200));"
                ]
              }
            }
          ]
        },
        {
          "name": "Create User",
          "request": {
            "method": "POST",
            "header": [
              {
                "key": "Content-Type",
                "value": "application/json"
              }
            ],
            "body": {
              "mode": "raw",
              "raw": "{\n  \"name\": \"Postman User {{testSuffix}}\",\n  \"email\": \"postman-{{testSuffix}}@example.com\",\n  \"username\": \"postman-{{testSuffix}}\",\n  \"password\": \"PostmanPassword123\",\n  \"roleId\": \"{{salesRoleId}}\",\n  \"isActive\": true\n}"
            },
            "url": "{{baseUrl}}/api/v1/users"
          },
          "event": [
            {
              "listen": "test",
              "script": {
                "type": "text/javascript",
                "exec": [
                  "pm.test('Status 201', () => pm.response.to.have.status(201));",
                  "pm.collectionVariables.set('userId', pm.response.json().data.id);"
                ]
              }
            }
          ]
        },
        {
          "name": "Get User Detail",
          "request": {
            "method": "GET",
            "url": "{{baseUrl}}/api/v1/users/{{userId}}"
          },
          "event": [
            {
              "listen": "test",
              "script": {
                "type": "text/javascript",
                "exec": [
                  "pm.test('Status 200', () => pm.response.to.have.status(200));"
                ]
              }
            }
          ]
        },
        {
          "name": "Update User",
          "request": {
            "method": "PATCH",
            "header": [
              {
                "key": "Content-Type",
                "value": "application/json"
              }
            ],
            "body": {
              "mode": "raw",
              "raw": "{\n  \"name\": \"Postman User Updated {{testSuffix}}\"\n}"
            },
            "url": "{{baseUrl}}/api/v1/users/{{userId}}"
          },
          "event": [
            {
              "listen": "test",
              "script": {
                "type": "text/javascript",
                "exec": [
                  "pm.test('Status 200', () => pm.response.to.have.status(200));"
                ]
              }
            }
          ]
        },
        {
          "name": "Set User Role",
          "request": {
            "method": "PUT",
            "header": [
              {
                "key": "Content-Type",
                "value": "application/json"
              }
            ],
            "body": {
              "mode": "raw",
              "raw": "{\n  \"roleId\": \"{{salesRoleId}}\"\n}"
            },
            "url": "{{baseUrl}}/api/v1/users/{{userId}}/role"
          },
          "event": [
            {
              "listen": "test",
              "script": {
                "type": "text/javascript",
                "exec": [
                  "pm.test('Status 200', () => pm.response.to.have.status(200));"
                ]
              }
            }
          ]
        },
        {
          "name": "Set User Branch",
          "request": {
            "method": "PUT",
            "header": [
              {
                "key": "Content-Type",
                "value": "application/json"
              }
            ],
            "body": {
              "mode": "raw",
              "raw": "{\n  \"branchId\": \"{{branchId}}\"\n}"
            },
            "url": "{{baseUrl}}/api/v1/users/{{userId}}/branch"
          },
          "event": [
            {
              "listen": "test",
              "script": {
                "type": "text/javascript",
                "exec": [
                  "pm.test('Status 200', () => pm.response.to.have.status(200));"
                ]
              }
            }
          ]
        }
      ]
    },
    {
      "name": "07 Merek",
      "item": [
        {
          "name": "List Mereks",
          "request": {
            "method": "GET",
            "url": "{{baseUrl}}/api/v1/mereks?page=1&limit=20"
          },
          "event": [
            {
              "listen": "test",
              "script": {
                "type": "text/javascript",
                "exec": [
                  "pm.test('Status 200', () => pm.response.to.have.status(200));"
                ]
              }
            }
          ]
        },
        {
          "name": "Create Merek",
          "request": {
            "method": "POST",
            "header": [
              {
                "key": "Content-Type",
                "value": "application/json"
              }
            ],
            "body": {
              "mode": "raw",
              "raw": "{\n  \"name\": \"Toyota {{testSuffix}}\",\n  \"isActive\": true\n}"
            },
            "url": "{{baseUrl}}/api/v1/mereks"
          },
          "event": [
            {
              "listen": "test",
              "script": {
                "type": "text/javascript",
                "exec": [
                  "pm.test('Status 201', () => pm.response.to.have.status(201));",
                  "pm.collectionVariables.set('merekId', pm.response.json().data.id);"
                ]
              }
            }
          ]
        },
        {
          "name": "Get Merek Detail",
          "request": {
            "method": "GET",
            "url": "{{baseUrl}}/api/v1/mereks/{{merekId}}"
          },
          "event": [
            {
              "listen": "test",
              "script": {
                "type": "text/javascript",
                "exec": [
                  "pm.test('Status 200', () => pm.response.to.have.status(200));"
                ]
              }
            }
          ]
        },
        {
          "name": "Update Merek",
          "request": {
            "method": "PATCH",
            "header": [
              {
                "key": "Content-Type",
                "value": "application/json"
              }
            ],
            "body": {
              "mode": "raw",
              "raw": "{\n  \"name\": \"Toyota Updated {{testSuffix}}\"\n}"
            },
            "url": "{{baseUrl}}/api/v1/mereks/{{merekId}}"
          },
          "event": [
            {
              "listen": "test",
              "script": {
                "type": "text/javascript",
                "exec": [
                  "pm.test('Status 200', () => pm.response.to.have.status(200));"
                ]
              }
            }
          ]
        }
      ]
    },
    {
      "name": "08 Tipe",
      "item": [
        {
          "name": "List Tipes",
          "request": {
            "method": "GET",
            "url": "{{baseUrl}}/api/v1/mereks/{{merekId}}/tipes?page=1&limit=20"
          },
          "event": [
            {
              "listen": "test",
              "script": {
                "type": "text/javascript",
                "exec": [
                  "pm.test('Status 200', () => pm.response.to.have.status(200));"
                ]
              }
            }
          ]
        },
        {
          "name": "Create Tipe",
          "request": {
            "method": "POST",
            "header": [
              {
                "key": "Content-Type",
                "value": "application/json"
              }
            ],
            "body": {
              "mode": "raw",
              "raw": "{\n  \"name\": \"Avanza {{testSuffix}}\",\n  \"isActive\": true\n}"
            },
            "url": "{{baseUrl}}/api/v1/mereks/{{merekId}}/tipes"
          },
          "event": [
            {
              "listen": "test",
              "script": {
                "type": "text/javascript",
                "exec": [
                  "pm.test('Status 201', () => pm.response.to.have.status(201));",
                  "pm.collectionVariables.set('tipeId', pm.response.json().data.id);"
                ]
              }
            }
          ]
        },
        {
          "name": "Get Tipe Detail",
          "request": {
            "method": "GET",
            "url": "{{baseUrl}}/api/v1/mereks/{{merekId}}/tipes/{{tipeId}}"
          },
          "event": [
            {
              "listen": "test",
              "script": {
                "type": "text/javascript",
                "exec": [
                  "pm.test('Status 200', () => pm.response.to.have.status(200));"
                ]
              }
            }
          ]
        },
        {
          "name": "Update Tipe",
          "request": {
            "method": "PATCH",
            "header": [
              {
                "key": "Content-Type",
                "value": "application/json"
              }
            ],
            "body": {
              "mode": "raw",
              "raw": "{\n  \"name\": \"Avanza Updated {{testSuffix}}\"\n}"
            },
            "url": "{{baseUrl}}/api/v1/mereks/{{merekId}}/tipes/{{tipeId}}"
          },
          "event": [
            {
              "listen": "test",
              "script": {
                "type": "text/javascript",
                "exec": [
                  "pm.test('Status 200', () => pm.response.to.have.status(200));"
                ]
              }
            }
          ]
        }
      ]
    },
    {
      "name": "09 Vendor",
      "item": [
        {
          "name": "List Vendors",
          "request": {
            "method": "GET",
            "url": "{{baseUrl}}/api/v1/vendors?page=1&limit=20"
          },
          "event": [
            {
              "listen": "test",
              "script": {
                "type": "text/javascript",
                "exec": [
                  "pm.test('Status 200', () => pm.response.to.have.status(200));"
                ]
              }
            }
          ]
        },
        {
          "name": "Create Vendor",
          "request": {
            "method": "POST",
            "header": [
              {
                "key": "Content-Type",
                "value": "application/json"
              }
            ],
            "body": {
              "mode": "raw",
              "raw": "{\n  \"name\": \"Vendor A {{testSuffix}}\",\n  \"address\": \"Jl. Raya No 1\",\n  \"phone\": \"08123456789\",\n  \"isActive\": true\n}"
            },
            "url": "{{baseUrl}}/api/v1/vendors"
          },
          "event": [
            {
              "listen": "test",
              "script": {
                "type": "text/javascript",
                "exec": [
                  "pm.test('Status 201', () => pm.response.to.have.status(201));",
                  "pm.collectionVariables.set('vendorId', pm.response.json().data.id);"
                ]
              }
            }
          ]
        },
        {
          "name": "Get Vendor Detail",
          "request": {
            "method": "GET",
            "url": "{{baseUrl}}/api/v1/vendors/{{vendorId}}"
          },
          "event": [
            {
              "listen": "test",
              "script": {
                "type": "text/javascript",
                "exec": [
                  "pm.test('Status 200', () => pm.response.to.have.status(200));"
                ]
              }
            }
          ]
        },
        {
          "name": "Update Vendor",
          "request": {
            "method": "PATCH",
            "header": [
              {
                "key": "Content-Type",
                "value": "application/json"
              }
            ],
            "body": {
              "mode": "raw",
              "raw": "{\n  \"name\": \"Vendor A Updated {{testSuffix}}\"\n}"
            },
            "url": "{{baseUrl}}/api/v1/vendors/{{vendorId}}"
          },
          "event": [
            {
              "listen": "test",
              "script": {
                "type": "text/javascript",
                "exec": [
                  "pm.test('Status 200', () => pm.response.to.have.status(200));"
                ]
              }
            }
          ]
        }
      ]
    },
    {
      "name": "10 Branch & Media",
      "item": [
        {
          "name": "List Branches",
          "request": {
            "method": "GET",
            "url": "{{baseUrl}}/api/v1/branches?page=1&limit=20"
          },
          "event": [
            {
              "listen": "test",
              "script": {
                "type": "text/javascript",
                "exec": [
                  "pm.test('Status 200', () => pm.response.to.have.status(200));"
                ]
              }
            }
          ]
        },
        {
          "name": "Create Branch",
          "request": {
            "method": "POST",
            "header": [
              {
                "key": "Content-Type",
                "value": "application/json"
              }
            ],
            "body": {
              "mode": "raw",
              "raw": "{\n  \"nama\": \"Kantor Pusat {{testSuffix}}\",\n  \"code\": \"KP_{{testSuffix}}\",\n  \"lokasi\": \"Jakarta\",\n  \"longlat\": \"-6.200000, 106.816666\",\n  \"kontak\": \"021-123456\",\n  \"picId\": \"{{userId}}\"\n}"
            },
            "url": "{{baseUrl}}/api/v1/branches"
          },
          "event": [
            {
              "listen": "test",
              "script": {
                "type": "text/javascript",
                "exec": [
                  "pm.test('Status 201', () => pm.response.to.have.status(201));",
                  "pm.collectionVariables.set('branchId', pm.response.json().data.id);"
                ]
              }
            }
          ]
        },
        {
          "name": "Upload Branch Image",
          "request": {
            "method": "POST",
            "header": [],
            "body": {
              "mode": "formdata",
              "formdata": [
                {
                  "key": "image",
                  "type": "file",
                  "src": []
                }
              ]
            },
            "url": "{{baseUrl}}/api/v1/branches/{{branchId}}/images"
          },
          "event": [
            {
              "listen": "test",
              "script": {
                "type": "text/javascript",
                "exec": [
                  "pm.test('Status 201', () => pm.response.to.have.status(201));",
                  "pm.collectionVariables.set('branchImageId', pm.response.json().data.id);"
                ]
              }
            }
          ]
        },
        {
          "name": "Get Media (Public)",
          "request": {
            "auth": {
              "type": "noauth"
            },
            "method": "GET",
            "url": "{{baseUrl}}/m/{{branchImageId}}"
          },
          "event": [
            {
              "listen": "test",
              "script": {
                "type": "text/javascript",
                "exec": [
                  "pm.test('Status 200', () => pm.response.to.have.status(200));"
                ]
              }
            }
          ]
        },
        {
          "name": "Get Branch Detail",
          "request": {
            "method": "GET",
            "url": "{{baseUrl}}/api/v1/branches/{{branchId}}"
          },
          "event": [
            {
              "listen": "test",
              "script": {
                "type": "text/javascript",
                "exec": [
                  "pm.test('Status 200', () => pm.response.to.have.status(200));"
                ]
              }
            }
          ]
        }
      ]
    },
    {
      "name": "13 Leasing",
      "item": [
        {
          "name": "List Leasing",
          "request": {
            "method": "GET",
            "url": "{{baseUrl}}/api/v1/leasings?page=1&limit=20"
          },
          "event": [
            {
              "listen": "test",
              "script": {
                "type": "text/javascript",
                "exec": [
                  "pm.test('Status 200', () => pm.response.to.have.status(200));"
                ]
              }
            }
          ]
        },
        {
          "name": "Create Leasing",
          "request": {
            "method": "POST",
            "header": [
              {
                "key": "Content-Type",
                "value": "application/json"
              }
            ],
            "body": {
              "mode": "raw",
              "raw": "{\n  \"name\": \"New Leasing {{testSuffix}}\",\n  \"code\": \"L001_{{testSuffix}}\",\n  \"isActive\": true\n}"
            },
            "url": "{{baseUrl}}/api/v1/leasings"
          },
          "event": [
            {
              "listen": "test",
              "script": {
                "type": "text/javascript",
                "exec": [
                  "pm.test('Status 201', () => pm.response.to.have.status(201));",
                  "pm.collectionVariables.set('LeasingId', pm.response.json().data.id);"
                ]
              }
            }
          ]
        },
        {
          "name": "Get Detail Leasing",
          "request": {
            "method": "GET",
            "url": "{{baseUrl}}/api/v1/leasings/{{LeasingId}}"
          },
          "event": [
            {
              "listen": "test",
              "script": {
                "type": "text/javascript",
                "exec": [
                  "pm.test('Status 200', () => pm.response.to.have.status(200));"
                ]
              }
            }
          ]
        },
        {
          "name": "Update Leasing",
          "request": {
            "method": "PATCH",
            "header": [
              {
                "key": "Content-Type",
                "value": "application/json"
              }
            ],
            "body": {
              "mode": "raw",
              "raw": "{\n  \"name\": \"Updated Leasing {{testSuffix}}\"\n}"
            },
            "url": "{{baseUrl}}/api/v1/leasings/{{LeasingId}}"
          },
          "event": [
            {
              "listen": "test",
              "script": {
                "type": "text/javascript",
                "exec": [
                  "pm.test('Status 200', () => pm.response.to.have.status(200));"
                ]
              }
            }
          ]
        }
      ]
    },
    {
      "name": "14 Sumber Lead",
      "item": [
        {
          "name": "List Sumber Lead",
          "request": {
            "method": "GET",
            "url": "{{baseUrl}}/api/v1/sumber-leads?page=1&limit=20"
          },
          "event": [
            {
              "listen": "test",
              "script": {
                "type": "text/javascript",
                "exec": [
                  "pm.test('Status 200', () => pm.response.to.have.status(200));"
                ]
              }
            }
          ]
        },
        {
          "name": "Create Sumber Lead",
          "request": {
            "method": "POST",
            "header": [
              {
                "key": "Content-Type",
                "value": "application/json"
              }
            ],
            "body": {
              "mode": "raw",
              "raw": "{\n  \"name\": \"New Sumber Lead {{testSuffix}}\",\n  \"code\": \"SL001_{{testSuffix}}\",\n  \"isActive\": true\n}"
            },
            "url": "{{baseUrl}}/api/v1/sumber-leads"
          },
          "event": [
            {
              "listen": "test",
              "script": {
                "type": "text/javascript",
                "exec": [
                  "pm.test('Status 201', () => pm.response.to.have.status(201));",
                  "pm.collectionVariables.set('SumberLeadId', pm.response.json().data.id);"
                ]
              }
            }
          ]
        },
        {
          "name": "Get Detail Sumber Lead",
          "request": {
            "method": "GET",
            "url": "{{baseUrl}}/api/v1/sumber-leads/{{SumberLeadId}}"
          },
          "event": [
            {
              "listen": "test",
              "script": {
                "type": "text/javascript",
                "exec": [
                  "pm.test('Status 200', () => pm.response.to.have.status(200));"
                ]
              }
            }
          ]
        },
        {
          "name": "Update Sumber Lead",
          "request": {
            "method": "PATCH",
            "header": [
              {
                "key": "Content-Type",
                "value": "application/json"
              }
            ],
            "body": {
              "mode": "raw",
              "raw": "{\n  \"name\": \"Updated Sumber Lead {{testSuffix}}\"\n}"
            },
            "url": "{{baseUrl}}/api/v1/sumber-leads/{{SumberLeadId}}"
          },
          "event": [
            {
              "listen": "test",
              "script": {
                "type": "text/javascript",
                "exec": [
                  "pm.test('Status 200', () => pm.response.to.have.status(200));"
                ]
              }
            }
          ]
        }
      ]
    },
    {
      "name": "15 Pengecekan",
      "item": [
        {
          "name": "List Pengecekan",
          "request": {
            "method": "GET",
            "url": "{{baseUrl}}/api/v1/pengecekans?page=1&limit=20"
          },
          "event": [
            {
              "listen": "test",
              "script": {
                "type": "text/javascript",
                "exec": [
                  "pm.test('Status 200', () => pm.response.to.have.status(200));"
                ]
              }
            }
          ]
        },
        {
          "name": "Create Pengecekan",
          "request": {
            "method": "POST",
            "header": [
              {
                "key": "Content-Type",
                "value": "application/json"
              }
            ],
            "body": {
              "mode": "raw",
              "raw": "{\n  \"name\": \"New Pengecekan {{testSuffix}}\",\n  \"code\": \"P001_{{testSuffix}}\",\n  \"isActive\": true\n}"
            },
            "url": "{{baseUrl}}/api/v1/pengecekans"
          },
          "event": [
            {
              "listen": "test",
              "script": {
                "type": "text/javascript",
                "exec": [
                  "pm.test('Status 201', () => pm.response.to.have.status(201));",
                  "pm.collectionVariables.set('PengecekanId', pm.response.json().data.id);"
                ]
              }
            }
          ]
        },
        {
          "name": "Get Detail Pengecekan",
          "request": {
            "method": "GET",
            "url": "{{baseUrl}}/api/v1/pengecekans/{{PengecekanId}}"
          },
          "event": [
            {
              "listen": "test",
              "script": {
                "type": "text/javascript",
                "exec": [
                  "pm.test('Status 200', () => pm.response.to.have.status(200));"
                ]
              }
            }
          ]
        },
        {
          "name": "Update Pengecekan",
          "request": {
            "method": "PATCH",
            "header": [
              {
                "key": "Content-Type",
                "value": "application/json"
              }
            ],
            "body": {
              "mode": "raw",
              "raw": "{\n  \"name\": \"Updated Pengecekan {{testSuffix}}\"\n}"
            },
            "url": "{{baseUrl}}/api/v1/pengecekans/{{PengecekanId}}"
          },
          "event": [
            {
              "listen": "test",
              "script": {
                "type": "text/javascript",
                "exec": [
                  "pm.test('Status 200', () => pm.response.to.have.status(200));"
                ]
              }
            }
          ]
        }
      ]
    },
    {
      "name": "16 Kategori Pengeluaran",
      "item": [
        {
          "name": "List Kategori Pengeluaran",
          "request": {
            "method": "GET",
            "url": "{{baseUrl}}/api/v1/kategori-pengeluarans?page=1&limit=20"
          },
          "event": [
            {
              "listen": "test",
              "script": {
                "type": "text/javascript",
                "exec": [
                  "pm.test('Status 200', () => pm.response.to.have.status(200));"
                ]
              }
            }
          ]
        },
        {
          "name": "Create Kategori Pengeluaran",
          "request": {
            "method": "POST",
            "header": [
              {
                "key": "Content-Type",
                "value": "application/json"
              }
            ],
            "body": {
              "mode": "raw",
              "raw": "{\n  \"name\": \"New Kategori Pengeluaran {{testSuffix}}\",\n  \"code\": \"KP001_{{testSuffix}}\",\n  \"isActive\": true\n}"
            },
            "url": "{{baseUrl}}/api/v1/kategori-pengeluarans"
          },
          "event": [
            {
              "listen": "test",
              "script": {
                "type": "text/javascript",
                "exec": [
                  "pm.test('Status 201', () => pm.response.to.have.status(201));",
                  "pm.collectionVariables.set('KategoriPengeluaranId', pm.response.json().data.id);"
                ]
              }
            }
          ]
        },
        {
          "name": "Get Detail Kategori Pengeluaran",
          "request": {
            "method": "GET",
            "url": "{{baseUrl}}/api/v1/kategori-pengeluarans/{{KategoriPengeluaranId}}"
          },
          "event": [
            {
              "listen": "test",
              "script": {
                "type": "text/javascript",
                "exec": [
                  "pm.test('Status 200', () => pm.response.to.have.status(200));"
                ]
              }
            }
          ]
        },
        {
          "name": "Update Kategori Pengeluaran",
          "request": {
            "method": "PATCH",
            "header": [
              {
                "key": "Content-Type",
                "value": "application/json"
              }
            ],
            "body": {
              "mode": "raw",
              "raw": "{\n  \"name\": \"Updated Kategori Pengeluaran {{testSuffix}}\"\n}"
            },
            "url": "{{baseUrl}}/api/v1/kategori-pengeluarans/{{KategoriPengeluaranId}}"
          },
          "event": [
            {
              "listen": "test",
              "script": {
                "type": "text/javascript",
                "exec": [
                  "pm.test('Status 200', () => pm.response.to.have.status(200));"
                ]
              }
            }
          ]
        }
      ]
    },
    {
      "name": "17 Metode Pembayaran",
      "item": [
        {
          "name": "List Metode Pembayaran",
          "request": {
            "method": "GET",
            "url": "{{baseUrl}}/api/v1/metode-pembayarans?page=1&limit=20"
          },
          "event": [
            {
              "listen": "test",
              "script": {
                "type": "text/javascript",
                "exec": [
                  "pm.test('Status 200', () => pm.response.to.have.status(200));"
                ]
              }
            }
          ]
        },
        {
          "name": "Create Metode Pembayaran",
          "request": {
            "method": "POST",
            "header": [
              {
                "key": "Content-Type",
                "value": "application/json"
              }
            ],
            "body": {
              "mode": "raw",
              "raw": "{\n  \"name\": \"New Metode Pembayaran {{testSuffix}}\",\n  \"code\": \"MP001_{{testSuffix}}\",\n  \"isActive\": true\n}"
            },
            "url": "{{baseUrl}}/api/v1/metode-pembayarans"
          },
          "event": [
            {
              "listen": "test",
              "script": {
                "type": "text/javascript",
                "exec": [
                  "pm.test('Status 201', () => pm.response.to.have.status(201));",
                  "pm.collectionVariables.set('MetodePembayaranId', pm.response.json().data.id);"
                ]
              }
            }
          ]
        },
        {
          "name": "Get Detail Metode Pembayaran",
          "request": {
            "method": "GET",
            "url": "{{baseUrl}}/api/v1/metode-pembayarans/{{MetodePembayaranId}}"
          },
          "event": [
            {
              "listen": "test",
              "script": {
                "type": "text/javascript",
                "exec": [
                  "pm.test('Status 200', () => pm.response.to.have.status(200));"
                ]
              }
            }
          ]
        },
        {
          "name": "Update Metode Pembayaran",
          "request": {
            "method": "PATCH",
            "header": [
              {
                "key": "Content-Type",
                "value": "application/json"
              }
            ],
            "body": {
              "mode": "raw",
              "raw": "{\n  \"name\": \"Updated Metode Pembayaran {{testSuffix}}\"\n}"
            },
            "url": "{{baseUrl}}/api/v1/metode-pembayarans/{{MetodePembayaranId}}"
          },
          "event": [
            {
              "listen": "test",
              "script": {
                "type": "text/javascript",
                "exec": [
                  "pm.test('Status 200', () => pm.response.to.have.status(200));"
                ]
              }
            }
          ]
        }
      ]
    },
    {
      "name": "18 Dokumen",
      "item": [
        {
          "name": "List Dokumen",
          "request": {
            "method": "GET",
            "url": "{{baseUrl}}/api/v1/dokumens?page=1&limit=20"
          },
          "event": [
            {
              "listen": "test",
              "script": {
                "type": "text/javascript",
                "exec": [
                  "pm.test('Status 200', () => pm.response.to.have.status(200));"
                ]
              }
            }
          ]
        },
        {
          "name": "Create Dokumen",
          "request": {
            "method": "POST",
            "header": [
              {
                "key": "Content-Type",
                "value": "application/json"
              }
            ],
            "body": {
              "mode": "raw",
              "raw": "{\n  \"name\": \"New Dokumen {{testSuffix}}\",\n  \"code\": \"D001_{{testSuffix}}\",\n  \"isActive\": true\n}"
            },
            "url": "{{baseUrl}}/api/v1/dokumens"
          },
          "event": [
            {
              "listen": "test",
              "script": {
                "type": "text/javascript",
                "exec": [
                  "pm.test('Status 201', () => pm.response.to.have.status(201));",
                  "pm.collectionVariables.set('DokumenId', pm.response.json().data.id);"
                ]
              }
            }
          ]
        },
        {
          "name": "Get Detail Dokumen",
          "request": {
            "method": "GET",
            "url": "{{baseUrl}}/api/v1/dokumens/{{DokumenId}}"
          },
          "event": [
            {
              "listen": "test",
              "script": {
                "type": "text/javascript",
                "exec": [
                  "pm.test('Status 200', () => pm.response.to.have.status(200));"
                ]
              }
            }
          ]
        },
        {
          "name": "Update Dokumen",
          "request": {
            "method": "PATCH",
            "header": [
              {
                "key": "Content-Type",
                "value": "application/json"
              }
            ],
            "body": {
              "mode": "raw",
              "raw": "{\n  \"name\": \"Updated Dokumen {{testSuffix}}\"\n}"
            },
            "url": "{{baseUrl}}/api/v1/dokumens/{{DokumenId}}"
          },
          "event": [
            {
              "listen": "test",
              "script": {
                "type": "text/javascript",
                "exec": [
                  "pm.test('Status 200', () => pm.response.to.have.status(200));"
                ]
              }
            }
          ]
        }
      ]
    },
    {
      "name": "19 Perlengkapan",
      "item": [
        {
          "name": "List Perlengkapan",
          "request": {
            "method": "GET",
            "url": "{{baseUrl}}/api/v1/perlengkapans?page=1&limit=20"
          },
          "event": [
            {
              "listen": "test",
              "script": {
                "type": "text/javascript",
                "exec": [
                  "pm.test('Status 200', () => pm.response.to.have.status(200));"
                ]
              }
            }
          ]
        },
        {
          "name": "Create Perlengkapan",
          "request": {
            "method": "POST",
            "header": [
              {
                "key": "Content-Type",
                "value": "application/json"
              }
            ],
            "body": {
              "mode": "raw",
              "raw": "{\n  \"name\": \"New Perlengkapan {{testSuffix}}\",\n  \"code\": \"P002_{{testSuffix}}\",\n  \"isActive\": true\n}"
            },
            "url": "{{baseUrl}}/api/v1/perlengkapans"
          },
          "event": [
            {
              "listen": "test",
              "script": {
                "type": "text/javascript",
                "exec": [
                  "pm.test('Status 201', () => pm.response.to.have.status(201));",
                  "pm.collectionVariables.set('PerlengkapanId', pm.response.json().data.id);"
                ]
              }
            }
          ]
        },
        {
          "name": "Get Detail Perlengkapan",
          "request": {
            "method": "GET",
            "url": "{{baseUrl}}/api/v1/perlengkapans/{{PerlengkapanId}}"
          },
          "event": [
            {
              "listen": "test",
              "script": {
                "type": "text/javascript",
                "exec": [
                  "pm.test('Status 200', () => pm.response.to.have.status(200));"
                ]
              }
            }
          ]
        },
        {
          "name": "Update Perlengkapan",
          "request": {
            "method": "PATCH",
            "header": [
              {
                "key": "Content-Type",
                "value": "application/json"
              }
            ],
            "body": {
              "mode": "raw",
              "raw": "{\n  \"name\": \"Updated Perlengkapan {{testSuffix}}\"\n}"
            },
            "url": "{{baseUrl}}/api/v1/perlengkapans/{{PerlengkapanId}}"
          },
          "event": [
            {
              "listen": "test",
              "script": {
                "type": "text/javascript",
                "exec": [
                  "pm.test('Status 200', () => pm.response.to.have.status(200));"
                ]
              }
            }
          ]
        }
      ]
    },
    {
      "name": "05 Cleanup",
      "description": "Jalankan setelah workflow utama. Urutan penting karena relasi database.",
      "item": [
        {
          "name": "Delete Perlengkapan",
          "request": {
            "method": "DELETE",
            "url": "{{baseUrl}}/api/v1/perlengkapans/{{PerlengkapanId}}"
          },
          "event": [
            {
              "listen": "test",
              "script": {
                "type": "text/javascript",
                "exec": [
                  "pm.test('Status 200', () => pm.response.to.have.status(200));"
                ]
              }
            }
          ]
        },
        {
          "name": "Delete Dokumen",
          "request": {
            "method": "DELETE",
            "url": "{{baseUrl}}/api/v1/dokumens/{{DokumenId}}"
          },
          "event": [
            {
              "listen": "test",
              "script": {
                "type": "text/javascript",
                "exec": [
                  "pm.test('Status 200', () => pm.response.to.have.status(200));"
                ]
              }
            }
          ]
        },
        {
          "name": "Delete Metode Pembayaran",
          "request": {
            "method": "DELETE",
            "url": "{{baseUrl}}/api/v1/metode-pembayarans/{{MetodePembayaranId}}"
          },
          "event": [
            {
              "listen": "test",
              "script": {
                "type": "text/javascript",
                "exec": [
                  "pm.test('Status 200', () => pm.response.to.have.status(200));"
                ]
              }
            }
          ]
        },
        {
          "name": "Delete Kategori Pengeluaran",
          "request": {
            "method": "DELETE",
            "url": "{{baseUrl}}/api/v1/kategori-pengeluarans/{{KategoriPengeluaranId}}"
          },
          "event": [
            {
              "listen": "test",
              "script": {
                "type": "text/javascript",
                "exec": [
                  "pm.test('Status 200', () => pm.response.to.have.status(200));"
                ]
              }
            }
          ]
        },
        {
          "name": "Delete Pengecekan",
          "request": {
            "method": "DELETE",
            "url": "{{baseUrl}}/api/v1/pengecekans/{{PengecekanId}}"
          },
          "event": [
            {
              "listen": "test",
              "script": {
                "type": "text/javascript",
                "exec": [
                  "pm.test('Status 200', () => pm.response.to.have.status(200));"
                ]
              }
            }
          ]
        },
        {
          "name": "Delete Sumber Lead",
          "request": {
            "method": "DELETE",
            "url": "{{baseUrl}}/api/v1/sumber-leads/{{SumberLeadId}}"
          },
          "event": [
            {
              "listen": "test",
              "script": {
                "type": "text/javascript",
                "exec": [
                  "pm.test('Status 200', () => pm.response.to.have.status(200));"
                ]
              }
            }
          ]
        },
        {
          "name": "Delete Leasing",
          "request": {
            "method": "DELETE",
            "url": "{{baseUrl}}/api/v1/leasings/{{LeasingId}}"
          },
          "event": [
            {
              "listen": "test",
              "script": {
                "type": "text/javascript",
                "exec": [
                  "pm.test('Status 200', () => pm.response.to.have.status(200));"
                ]
              }
            }
          ]
        },
        {
          "name": "Delete Branch Image",
          "request": {
            "method": "DELETE",
            "url": "{{baseUrl}}/api/v1/branches/{{branchId}}/images/{{branchImageId}}"
          },
          "event": [
            {
              "listen": "test",
              "script": {
                "type": "text/javascript",
                "exec": [
                  "pm.test('Status 200', () => pm.response.to.have.status(200));"
                ]
              }
            }
          ]
        },
        {
          "name": "Delete Branch",
          "request": {
            "method": "DELETE",
            "url": "{{baseUrl}}/api/v1/branches/{{branchId}}"
          },
          "event": [
            {
              "listen": "test",
              "script": {
                "type": "text/javascript",
                "exec": [
                  "pm.test('Status 200', () => pm.response.to.have.status(200));"
                ]
              }
            }
          ]
        },
        {
          "name": "Delete Vendor",
          "request": {
            "method": "DELETE",
            "url": "{{baseUrl}}/api/v1/vendors/{{vendorId}}"
          },
          "event": [
            {
              "listen": "test",
              "script": {
                "type": "text/javascript",
                "exec": [
                  "pm.test('Status 200', () => pm.response.to.have.status(200));"
                ]
              }
            }
          ]
        },
        {
          "name": "Delete Tipe",
          "request": {
            "method": "DELETE",
            "url": "{{baseUrl}}/api/v1/mereks/{{merekId}}/tipes/{{tipeId}}"
          },
          "event": [
            {
              "listen": "test",
              "script": {
                "type": "text/javascript",
                "exec": [
                  "pm.test('Status 200', () => pm.response.to.have.status(200));"
                ]
              }
            }
          ]
        },
        {
          "name": "Delete Merek",
          "request": {
            "method": "DELETE",
            "url": "{{baseUrl}}/api/v1/mereks/{{merekId}}"
          },
          "event": [
            {
              "listen": "test",
              "script": {
                "type": "text/javascript",
                "exec": [
                  "pm.test('Status 200', () => pm.response.to.have.status(200));"
                ]
              }
            }
          ]
        },
        {
          "name": "Delete User",
          "request": {
            "method": "DELETE",
            "url": "{{baseUrl}}/api/v1/users/{{userId}}"
          },
          "event": [
            {
              "listen": "test",
              "script": {
                "type": "text/javascript",
                "exec": [
                  "pm.test('Status 200', () => pm.response.to.have.status(200));"
                ]
              }
            }
          ]
        },
        {
          "name": "Delete Role",
          "request": {
            "method": "DELETE",
            "url": "{{baseUrl}}/api/v1/roles/{{roleId}}"
          },
          "event": [
            {
              "listen": "test",
              "script": {
                "type": "text/javascript",
                "exec": [
                  "pm.test('Status 200', () => pm.response.to.have.status(200));"
                ]
              }
            }
          ]
        },
        {
          "name": "Delete Permission",
          "request": {
            "method": "DELETE",
            "url": "{{baseUrl}}/api/v1/menus/{{menuId}}/permissions/{{permissionId}}"
          },
          "event": [
            {
              "listen": "test",
              "script": {
                "type": "text/javascript",
                "exec": [
                  "pm.test('Status 200', () => pm.response.to.have.status(200));"
                ]
              }
            }
          ]
        },
        {
          "name": "Delete Menu",
          "request": {
            "method": "DELETE",
            "url": "{{baseUrl}}/api/v1/menus/{{menuId}}"
          },
          "event": [
            {
              "listen": "test",
              "script": {
                "type": "text/javascript",
                "exec": [
                  "pm.test('Status 200', () => pm.response.to.have.status(200));"
                ]
              }
            }
          ]
        },
        {
          "name": "Delete Group Menu",
          "request": {
            "method": "DELETE",
            "url": "{{baseUrl}}/api/v1/menus/groups/{{groupMenuId}}"
          },
          "event": [
            {
              "listen": "test",
              "script": {
                "type": "text/javascript",
                "exec": [
                  "pm.test('Status 200', () => pm.response.to.have.status(200));"
                ]
              }
            }
          ]
        }
      ]
    },
    {
      "name": "06 Session",
      "item": [
        {
          "name": "Logout Current Session",
          "request": {
            "method": "POST",
            "url": "{{baseUrl}}/api/v1/auth/logout"
          },
          "event": [
            {
              "listen": "test",
              "script": {
                "type": "text/javascript",
                "exec": [
                  "pm.test('Status 200', () => pm.response.to.have.status(200));",
                  "pm.collectionVariables.set('accessToken', '');",
                  "pm.collectionVariables.set('refreshToken', '');"
                ]
              }
            }
          ]
        },
        {
          "name": "Login Again",
          "request": {
            "auth": {
              "type": "noauth"
            },
            "method": "POST",
            "header": [
              {
                "key": "Content-Type",
                "value": "application/json"
              }
            ],
            "body": {
              "mode": "raw",
              "raw": "{\n  \"identifier\": \"{{username}}\",\n  \"password\": \"{{password}}\"\n}"
            },
            "url": "{{baseUrl}}/api/v1/auth/login"
          },
          "event": [
            {
              "listen": "test",
              "script": {
                "type": "text/javascript",
                "exec": [
                  "pm.test('Status 200', () => pm.response.to.have.status(200));",
                  "const data = pm.response.json().data;",
                  "pm.collectionVariables.set('accessToken', data.accessToken);",
                  "pm.collectionVariables.set('refreshToken', data.refreshToken);"
                ]
              }
            }
          ]
        },
        {
          "name": "Logout All Sessions",
          "request": {
            "method": "POST",
            "url": "{{baseUrl}}/api/v1/auth/logout-all"
          },
          "event": [
            {
              "listen": "test",
              "script": {
                "type": "text/javascript",
                "exec": [
                  "pm.test('Status 200', () => pm.response.to.have.status(200));",
                  "pm.collectionVariables.set('accessToken', '');",
                  "pm.collectionVariables.set('refreshToken', '');"
                ]
              }
            }
          ]
        }
      ]
    }
  ]
}